<Stats deaths="907" kills="246" player_kills="3" player_projectile_count="0" >
  <death_map>
    <E key=" | $damage_projectile" value="2" >
    </E>
    <E key="NULL | $damage_drowning" value="7" >
    </E>
    <E key="NULL | $damage_electricity" value="1" >
    </E>
    <E key="NULL | $damage_explosion" value="35" >
    </E>
    <E key="NULL | $damage_fire" value="88" >
    </E>
    <E key="NULL | $damage_melee" value="1" >
    </E>
    <E key="NULL | $damage_physicshit" value="21" >
    </E>
    <E key="NULL | $damage_projectile" value="2" >
    </E>
    <E key="NULL | kill sync" value="5" >
    </E>
    <E key="firemage_weak | $damage_explosion" value="5" >
    </E>
    <E key="firemage_weak | $damage_projectile" value="1" >
    </E>
    <E key="longleg | $damage_melee" value="3" >
    </E>
    <E key="miner_weak | $damage_explosion" value="43" >
    </E>
    <E key="miner_weak | $damage_melee" value="9" >
    </E>
    <E key="miner_weak | $damage_projectile" value="1" >
    </E>
    <E key="player | $damage_explosion" value="7" >
    </E>
    <E key="player | $damage_melee" value="3" >
    </E>
    <E key="player | $damage_plasmabeam" value="1" >
    </E>
    <E key="player | $damage_projectile" value="422" >
    </E>
    <E key="player | $damage_slice" value="145" >
    </E>
    <E key="player_rng_items | $damage_projectile" value="1" >
    </E>
    <E key="shaman | $damage_projectile" value="2" >
    </E>
    <E key="shotgunner_weak | $damage_melee" value="3" >
    </E>
    <E key="shotgunner_weak | $damage_projectile" value="40" >
    </E>
    <E key="slimeshooter_nontoxic | $damage_explosion" value="1" >
    </E>
    <E key="slimeshooter_nontoxic | $damage_projectile" value="2" >
    </E>
    <E key="slimeshooter_weak | $damage_explosion" value="21" >
    </E>
    <E key="slimeshooter_weak | $damage_projectile" value="1" >
    </E>
    <E key="wizard_dark | $damage_projectile" value="1" >
    </E>
    <E key="worm | worm bite" value="9" >
    </E>
    <E key="worm_big | worm bite" value="1" >
    </E>
    <E key="worm_tiny | worm bite" value="4" >
    </E>
    <E key="zombie | $damage_melee" value="1" >
    </E>
    <E key="zombie_weak | $damage_melee" value="18" >
    </E>
  </death_map>
  <kill_map>
    <E key="bomb" value="1" >
    </E>
    <E key="firemage_weak" value="2" >
    </E>
    <E key="longleg" value="67" >
    </E>
    <E key="miner_weak" value="17" >
    </E>
    <E key="player" value="3" >
    </E>
    <E key="potion" value="1" >
    </E>
    <E key="sheep" value="1" >
    </E>
    <E key="sheep_fly" value="1" >
    </E>
    <E key="shotgunner_weak" value="12" >
    </E>
    <E key="slimeshooter_weak" value="22" >
    </E>
    <E key="tnt" value="1" >
    </E>
    <E key="zombie_weak" value="118" >
    </E>
  </kill_map>
</Stats>
