<Stats BUILD_NAME="Noita-Build-Aug 12 2024-21:48:01" >
  <stats biomes_visited_with_wands="11" damage_taken="54.6916" dead="1" death_count="0" death_pos.x="-1387.61" death_pos.y="11474" enemies_killed="174" gold="1277" gold_all="5387" gold_infinite="0" healed="0" heart_containers="0" hp="100" items="41" kicks="101" killed_by="Turso | melee" killed_by_extra="" places_visited="11" playtime="3232.6" playtime_str="0:53:52" projectiles_shot="2533" streaks="0" teleports="0" wands_edited="7" world_seed="51819541" >
  </stats>
  <biome_baseline biomes_visited_with_wands="2" damage_taken="6.30102" dead="0" death_count="0" death_pos.x="0" death_pos.y="0" enemies_killed="29" gold="651" gold_all="1251" gold_infinite="0" healed="0" heart_containers="0" hp="100" items="13" kicks="46" killed_by="" killed_by_extra="" places_visited="2" playtime="806.4" playtime_str="0:13:26" projectiles_shot="285" streaks="0" teleports="0" wands_edited="4" world_seed="51819541" >
  </biome_baseline>
  <item_map>
  </item_map>
  <biomes_visited>
    <E key="$biome_coalmine" value="1" >
    </E>
    <E key="$biome_crypt" value="1" >
    </E>
    <E key="$biome_desert" value="1" >
    </E>
    <E key="$biome_excavationsite" value="1" >
    </E>
    <E key="$biome_fungicave" value="1" >
    </E>
    <E key="$biome_holymountain" value="1" >
    </E>
    <E key="$biome_orbroom" value="1" >
    </E>
    <E key="$biome_rainforest" value="1" >
    </E>
    <E key="$biome_snowcastle" value="1" >
    </E>
    <E key="$biome_snowcave" value="1" >
    </E>
    <E key="$biome_vault" value="1" >
    </E>
  </biomes_visited>
</Stats>
